scigee/__init__.py
scigee/geeface.py
scigee/utils.py
scigee/depracated/__init__.py
scigee/depracated/canvas.py
scigee/depracated/chart.py
scigee/depracated/cloud_masking.py
scigee/depracated/ee_export.py
scigee/depracated/geeface.py
scigee/depracated/geeface_lite.py
scigee/depracated/geelite.py
scigee/depracated/utilize.py
scigee/depracated/utils.py
scigee-0.0.36.dist-info/METADATA
scigee-0.0.36.dist-info/WHEEL
scigee-0.0.36.dist-info/top_level.txt
scigee-0.0.36.dist-info/RECORD
