Metadata-Version: 2.1
Name: scigee
Version: 0.0.36
Summary: For faster proccessing geofile
Home-page: https://github.com/soonyenju/scigee
Author: Songyan Zhu
Author-email: Songyan.Zhu@outlool.com
License: MIT Licence
Keywords: easy geo warpper,atmospheric data,satellite data,flux
Platform: any
Requires-Dist: geetools
